mimizuku/__init__.py
mimizuku/model.py
mimizuku/utils.py
mimizuku/rules/__init__.py
mimizuku/rules/audit_command.py
mimizuku/rules/base.py
mimizuku/rules/fs_notify.py
mimizuku-0.2.34.dist-info/METADATA
mimizuku-0.2.34.dist-info/WHEEL
mimizuku-0.2.34.dist-info/entry_points.txt
mimizuku-0.2.34.dist-info/top_level.txt
mimizuku-0.2.34.dist-info/RECORD
