Metadata-Version: 2.1
Name: mimizuku
Version: 0.2.34
Summary: A package for anomaly detection using Isolation Forest for Wazuh Alerts
Home-page: https://github.com/pyama86/mimizuku
Author: pyama86
Author-email: www.kazu.com@gmail.com
Classifier: Programming Language :: Python :: 3
Classifier: License :: OSI Approved :: MIT License
Classifier: Operating System :: OS Independent
Requires-Python: >=3.6
Requires-Dist: numpy
Requires-Dist: pandas
Requires-Dist: scikit-learn
Requires-Dist: joblib
Requires-Dist: orjson
